README.md
setup.cfg
setup.py
wwpdb/__init__.py
wwpdb.apps.ann_tasks_v2.egg-info/PKG-INFO
wwpdb.apps.ann_tasks_v2.egg-info/SOURCES.txt
wwpdb.apps.ann_tasks_v2.egg-info/dependency_links.txt
wwpdb.apps.ann_tasks_v2.egg-info/not-zip-safe
wwpdb.apps.ann_tasks_v2.egg-info/requires.txt
wwpdb.apps.ann_tasks_v2.egg-info/top_level.txt
wwpdb/apps/__init__.py
wwpdb/apps/ann_tasks_v2/__init__.py
wwpdb/apps/ann_tasks_v2/assembly/AssemblyInput.py
wwpdb/apps/ann_tasks_v2/assembly/AssemblySelect.py
wwpdb/apps/ann_tasks_v2/assembly/__init__.py
wwpdb/apps/ann_tasks_v2/check/Check.py
wwpdb/apps/ann_tasks_v2/check/EmMapCheck.py
wwpdb/apps/ann_tasks_v2/check/EmdXmlCheck.py
wwpdb/apps/ann_tasks_v2/check/ExtraCheck.py
wwpdb/apps/ann_tasks_v2/check/FormatCheck.py
wwpdb/apps/ann_tasks_v2/check/GeometryCalc.py
wwpdb/apps/ann_tasks_v2/check/GeometryCheck.py
wwpdb/apps/ann_tasks_v2/check/XmlCheck.py
wwpdb/apps/ann_tasks_v2/check/__init__.py
wwpdb/apps/ann_tasks_v2/correspnd/CorresPNDGenerator.py
wwpdb/apps/ann_tasks_v2/correspnd/CorresPNDTemplate.py
wwpdb/apps/ann_tasks_v2/correspnd/ValidateXml.py
wwpdb/apps/ann_tasks_v2/correspnd/__init__.py
wwpdb/apps/ann_tasks_v2/density/DensityGeneration.py
wwpdb/apps/ann_tasks_v2/density/__init__.py
wwpdb/apps/ann_tasks_v2/depict/PdbxDepictBootstrapBase.py
wwpdb/apps/ann_tasks_v2/depict/__init__.py
wwpdb/apps/ann_tasks_v2/editCoord/CSEditorForm.py
wwpdb/apps/ann_tasks_v2/editCoord/CSEditorUpdate.py
wwpdb/apps/ann_tasks_v2/editCoord/CoordEditorForm.py
wwpdb/apps/ann_tasks_v2/editCoord/CoordEditorForm_v2.py
wwpdb/apps/ann_tasks_v2/editCoord/CoordEditorUpdate.py
wwpdb/apps/ann_tasks_v2/editCoord/__init__.py
wwpdb/apps/ann_tasks_v2/em3d/EmAutoFix.py
wwpdb/apps/ann_tasks_v2/em3d/EmEditUtils.py
wwpdb/apps/ann_tasks_v2/em3d/EmHeaderUtils.py
wwpdb/apps/ann_tasks_v2/em3d/EmMapAutoFixVers.py
wwpdb/apps/ann_tasks_v2/em3d/EmModelUtils.py
wwpdb/apps/ann_tasks_v2/em3d/EmUtils.py
wwpdb/apps/ann_tasks_v2/em3d/__init__.py
wwpdb/apps/ann_tasks_v2/expIoUtils/MtzTommCIF.py
wwpdb/apps/ann_tasks_v2/expIoUtils/PdbxExpIoUtils.py
wwpdb/apps/ann_tasks_v2/expIoUtils/PdbxExpUpdate.py
wwpdb/apps/ann_tasks_v2/expIoUtils/ReSetFreeRinSFmmCIF.py
wwpdb/apps/ann_tasks_v2/expIoUtils/__init__.py
wwpdb/apps/ann_tasks_v2/io/PdbxIoUtils.py
