Metadata-Version: 2.4
Name: wwpdb.apps.ann_tasks_v2
Version: 0.44.1
Summary: wwPDB annotation/review/status/validation module backend
Home-page: https://github.com/rcsb/py-wwpdb_apps_ann_tasks_v2
Author: Ezra Peisach
Author-email: ezra.peisach@rcsb.org
License: Apache 2.0
Classifier: Development Status :: 3 - Alpha
Classifier: Intended Audience :: Developers
Classifier: Natural Language :: English
Classifier: License :: OSI Approved :: Apache Software License
Classifier: Programming Language :: Python
Classifier: Programming Language :: Python :: 2.7
Classifier: Programming Language :: Python :: 3
Classifier: Programming Language :: Python :: 3.6
Classifier: Programming Language :: Python :: 3.7
Requires-Dist: wwpdb.utils.config>=0.45
Requires-Dist: wwpdb.apps.wf_engine
Requires-Dist: wwpdb.io
Requires-Dist: wwpdb.utils.db[status]>=0.6
Requires-Dist: wwpdb.utils.emdb~=1.0
Requires-Dist: wwpdb.utils.wf>=0.13
Requires-Dist: wwpdb.utils.session
Requires-Dist: mmcif>=0.25
Requires-Dist: wwpdb.utils.dp~=0.54
Requires-Dist: wwpdb.utils.detach
Requires-Dist: wwpdb.utils.nmr>=0.24
Requires-Dist: mmcif.utils~=0.22
Requires-Dist: matplotlib
Requires-Dist: pygal
Provides-Extra: buster
Requires-Dist: wwpdb.apps.validation~=2.3; extra == "buster"
Provides-Extra: dev
Requires-Dist: check-manifest; extra == "dev"
Provides-Extra: test
Requires-Dist: coverage; extra == "test"
Dynamic: author
Dynamic: author-email
Dynamic: classifier
Dynamic: description
Dynamic: home-page
Dynamic: license
Dynamic: provides-extra
Dynamic: requires-dist
Dynamic: summary
